README.rst
setup.py
django_multi_form.egg-info/PKG-INFO
django_multi_form.egg-info/SOURCES.txt
django_multi_form.egg-info/dependency_links.txt
django_multi_form.egg-info/not-zip-safe
django_multi_form.egg-info/top_level.txt
multi_form/__init__.py
multi_form/generic.py
multi_form/mixin.py