Metadata-Version: 1.0
Name: django-multi-form
Version: 0.5
Summary: Django class based views for using more than one Form in a single view.
Home-page: https://github.com/Firexd2/django-multi-form
Author: firexd2
Author-email: den@beloglazov.me
License: MIT
Platform: UNKNOWN
